magic_defis/__init__.py
magic_defis/defis.py
magic_defis-0.3.dist-info/METADATA
magic_defis-0.3.dist-info/WHEEL
magic_defis-0.3.dist-info/top_level.txt
magic_defis-0.3.dist-info/RECORD
