Metadata-Version: 2.1
Name: magic-defis
Version: 0.3
Summary: Defis python Magic Makers
Home-page: https://magicmakers.fr
Author: Magic Team
Author-email: pedagogie@magicmakers.fr
License: MIT
Platform: UNKNOWN
Requires-Dist: numpy
Requires-Dist: pillow
Requires-Dist: pydub
Requires-Dist: colorama
Requires-Dist: termcolor
